simplebot_facts/__init__.py
simplebot_facts/_version.py
simplebot_facts-1.0.1.dist-info/LICENSE
simplebot_facts-1.0.1.dist-info/METADATA
simplebot_facts-1.0.1.dist-info/WHEEL
simplebot_facts-1.0.1.dist-info/entry_points.txt
simplebot_facts-1.0.1.dist-info/top_level.txt
simplebot_facts-1.0.1.dist-info/RECORD
