Metadata-Version: 2.1
Name: simplebot-facts
Version: 1.0.1
Summary: Get random facts in Delta Chat (SimpleBot plugin)
Home-page: https://github.com/simplebot-org/simplebot_facts
Author: adbenitez
Author-email: adbenitez@nauta.cu
License: MPL
Keywords: simplebot plugin deltachat
Platform: UNKNOWN
Classifier: Development Status :: 4 - Beta
Classifier: Environment :: Plugins
Classifier: Programming Language :: Python :: 3
Classifier: License :: OSI Approved :: Mozilla Public License 2.0 (MPL 2.0)
Classifier: Operating System :: OS Independent
Classifier: Topic :: Utilities
License-File: LICENSE
Requires-Dist: simplebot (>=2.4.0)
Requires-Dist: requests (>=2.26.0)
Requires-Dist: beautifulsoup4 (>=4.10.0)
Provides-Extra: dev
Requires-Dist: simplebot (>=2.4.0) ; extra == 'dev'
Requires-Dist: requests (>=2.26.0) ; extra == 'dev'
Requires-Dist: beautifulsoup4 (>=4.10.0) ; extra == 'dev'
Requires-Dist: pytest (>=6.2.5) ; extra == 'dev'
Requires-Dist: black (>=21.12b0) ; extra == 'dev'
Requires-Dist: mypy (>=0.930) ; extra == 'dev'
Requires-Dist: isort (>=5.10.1) ; extra == 'dev'
Requires-Dist: pylint (>=2.12.2) ; extra == 'dev'
Requires-Dist: pylama (>=8.3.6) ; extra == 'dev'
Requires-Dist: types-requests (>=2.26.3) ; extra == 'dev'
Provides-Extra: test
Requires-Dist: pytest (>=6.2.5) ; extra == 'test'
